{
  "entities": {
    "UserProfile": {
      "title": "User Profile",
      "description": "Represents a user's profile information.",
      "type": "object",
      "properties": {
        "uid": {
          "type": "string",
          "description": "The user's unique ID."
        },
        "email": {
          "type": "string",
          "format": "email",
          "description": "The user's email address."
        },
        "displayName": {
          "type": "string",
          "description": "The user's display name."
        }
      },
      "required": ["uid", "email"]
    },
    "OperatorProductionInput": {
      "title": "Operator Production Input",
      "description": "Represents a single production entry from an operator.",
      "type": "object",
      "properties": {
        "operatorId": {
          "type": "string",
          "description": "The ID of the operator."
        },
        "machineId": {
          "type": "string",
          "description": "The ID of the machine used."
        },
        "quantityProduced": {
          "type": "number",
          "description": "The number of units produced."
        },
        "productionTimeSeconds": {
          "type": "number",
          "description": "The time taken for production in seconds."
        },
        "timestamp": {
          "type": "number",
          "description": "The server timestamp of the entry (milliseconds since epoch)."
        },
        "formsNumber": {
          "type": "string",
          "description": "Optional forms number associated with the production."
        },
        "factory": {
          "type": "string",
          "description": "The factory where the production took place."
        },
        "operationCount": {
          "type": "number",
          "description": "The number of operations performed."
        },
        "status": {
          "type": "string",
          "description": "The current status of the production entry.",
          "enum": ["Fila de produção", "Em produção", "Encerrado", "Rejeitado", "Enviado"]
        },
        "activityType": {
          "type": "string",
          "description": "The type of activity performed.",
          "enum": ["USINAGEM", "PROGRAMAÇÃO"]
        }
      },
      "required": ["operatorId", "machineId", "quantityProduced", "productionTimeSeconds", "timestamp", "factory", "status", "activityType"]
    },
    "ProductionLossInput": {
      "title": "Production Loss Input",
      "description": "Represents a single entry for production loss.",
      "type": "object",
      "properties": {
        "operatorId": {
          "type": "string",
          "description": "The ID of the operator reporting the loss."
        },
        "factory": {
          "type": "string",
          "description": "The factory where the loss occurred."
        },
        "machineId": {
          "type": "string",
          "description": "The ID of the machine related to the loss."
        },
        "quantityLost": {
          "type": "number",
          "description": "The number of units lost."
        },
        "reason": {
          "type": "string",
          "description": "The reason for the production loss."
        },
        "timeLostMinutes": {
          "type": "number",
          "description": "The downtime in minutes due to the loss."
        },
        "timestamp": {
          "type": "number",
          "description": "The server timestamp of the loss entry (milliseconds since epoch)."
        }
      },
      "required": ["operatorId", "factory", "machineId", "quantityLost", "reason", "timeLostMinutes", "timestamp"]
    }
  },
  "auth": {
    "providers": ["email-password"]
  },
  "firestore": {
    "/users/{userId}": {
      "schema": {
        "$ref": "#/backend/entities/UserProfile"
      },
      "description": "Stores public profile information for each user."
    }
  }
}
